kontra/__init__.py
kontra/errors.py
kontra/logging.py
kontra/version.py
kontra/api/__init__.py
kontra/api/compare.py
kontra/api/decorators.py
kontra/api/results.py
kontra/api/rules.py
kontra/cli/__init__.py
kontra/cli/constants.py
kontra/cli/main.py
kontra/cli/renderers.py
kontra/cli/utils.py
kontra/cli/commands/__init__.py
kontra/cli/commands/config.py
kontra/cli/commands/diff.py
kontra/cli/commands/history.py
kontra/cli/commands/profile.py
kontra/cli/commands/validate.py
kontra/config/__init__.py
kontra/config/loader.py
kontra/config/models.py
kontra/config/settings.py
kontra/connectors/__init__.py
kontra/connectors/db_utils.py
kontra/connectors/detection.py
kontra/connectors/handle.py
kontra/connectors/postgres.py
kontra/connectors/sqlserver.py
kontra/engine/__init__.py
kontra/engine/engine.py
kontra/engine/paths.py
kontra/engine/result.py
kontra/engine/sql_utils.py
kontra/engine/sql_validator.py
kontra/engine/stats.py
kontra/engine/types.py
kontra/engine/backends/duckdb_session.py
kontra/engine/backends/duckdb_utils.py
kontra/engine/backends/polars_backend.py
kontra/engine/executors/__init__.py
kontra/engine/executors/base.py
kontra/engine/executors/database_base.py
kontra/engine/executors/duckdb_sql.py
kontra/engine/executors/postgres_sql.py
kontra/engine/executors/registry.py
kontra/engine/executors/sqlserver_sql.py
kontra/engine/materializers/__init__.py
kontra/engine/materializers/base.py
kontra/engine/materializers/duckdb.py
kontra/engine/materializers/factory.py
kontra/engine/materializers/polars_connector.py
kontra/engine/materializers/postgres.py
kontra/engine/materializers/registry.py
kontra/engine/materializers/sqlserver.py
kontra/preplan/__init__.py
kontra/preplan/planner.py
kontra/preplan/postgres.py
kontra/preplan/sqlserver.py
kontra/preplan/types.py
kontra/probes/__init__.py
kontra/probes/compare.py
kontra/probes/relationship.py
kontra/probes/utils.py
kontra/reporters/__init__.py
kontra/reporters/json_reporter.py
kontra/reporters/rich_reporter.py
kontra-0.6.1.dist-info/licenses/LICENSE
kontra-0.6.1.dist-info/METADATA
kontra-0.6.1.dist-info/WHEEL
kontra-0.6.1.dist-info/entry_points.txt
kontra-0.6.1.dist-info/top_level.txt
kontra-0.6.1.dist-info/RECORD
