Metadata-Version: 2.4
Name: kontra
Version: 0.6.1
Summary: Developer-first data quality engine
Author: Saevarlb
License: Apache-2.0
Project-URL: Homepage, https://github.com/Saevarl/Kontra
Project-URL: Documentation, https://github.com/Saevarl/Kontra#readme
Project-URL: Repository, https://github.com/Saevarl/Kontra
Project-URL: Issues, https://github.com/Saevarl/Kontra/issues
Keywords: data-quality,validation,data-contracts,polars,duckdb
Classifier: Development Status :: 4 - Beta
Classifier: Intended Audience :: Developers
Classifier: License :: OSI Approved :: Apache Software License
Classifier: Programming Language :: Python :: 3
Classifier: Programming Language :: Python :: 3.10
Classifier: Programming Language :: Python :: 3.11
Classifier: Programming Language :: Python :: 3.12
Classifier: Programming Language :: Python :: 3.13
Classifier: Topic :: Database
Classifier: Topic :: Software Development :: Quality Assurance
Requires-Python: >=3.10
License-File: LICENSE
Requires-Dist: polars>=0.20.0
Requires-Dist: duckdb>=0.9.0
Requires-Dist: pydantic>=2.0.0
Requires-Dist: typer>=0.9.0
Requires-Dist: rich>=13.0.0
Requires-Dist: pyarrow>=14.0.0
Requires-Dist: pyyaml>=6.0.0
Requires-Dist: sqlglot>=20.0.0
Provides-Extra: s3
Requires-Dist: s3fs>=2024.6.0; extra == "s3"
Provides-Extra: postgres
Requires-Dist: psycopg[binary]>=3.0.0; extra == "postgres"
Provides-Extra: sqlserver
Requires-Dist: pymssql>=2.2.0; extra == "sqlserver"
Provides-Extra: all
Requires-Dist: s3fs>=2024.6.0; extra == "all"
Requires-Dist: psycopg[binary]>=3.0.0; extra == "all"
Requires-Dist: pymssql>=2.2.0; extra == "all"
Provides-Extra: dev
Requires-Dist: pytest>=8.0.0; extra == "dev"
Requires-Dist: pytest-cov>=4.0.0; extra == "dev"
Requires-Dist: ruff>=0.1.0; extra == "dev"
Dynamic: license-file
